Pillows/__init__.py
Pillows/files.py
Pillows-0.0.13.dist-info/METADATA
Pillows-0.0.13.dist-info/WHEEL
Pillows-0.0.13.dist-info/top_level.txt
Pillows-0.0.13.dist-info/RECORD
