Metadata-Version: 2.1
Name: Pillows
Version: 0.0.13
Summary: Pillows
Author: xhi
Author-email: <xihshan@info.in>
Keywords: python
Classifier: Programming Language :: Python :: 3
